<?xml version="1.0" encoding="utf-8" ?>
<dwsync>
<file name="compression.jpg" server="thewarfields.com//www/" local="129781988982664054" remote="129781954200000000" />
<file name="downcut.jpg" server="thewarfields.com//www/" local="129781990160231407" remote="129781954200000000" />
<file name="upcut.jpg" server="thewarfields.com//www/" local="129781990198073572" remote="129781954200000000" />
<file name="diamondcut.jpg" server="thewarfields.com//www/" local="129782001064495096" remote="129781965600000000" />
<file name="compression.jpg" server="NONA.lunarservers.com//www/" local="129781988982664054" remote="129854077200000000" />
<file name="diamondcut.jpg" server="NONA.lunarservers.com//www/" local="129782001064495096" remote="129854077200000000" />
<file name="downcut.jpg" server="NONA.lunarservers.com//www/" local="129781990160231407" remote="129854077200000000" />
<file name="upcut.jpg" server="NONA.lunarservers.com//www/" local="129781990198073572" remote="129854077200000000" />
</dwsync>